normalizacao/__init__.py
normalizacao/normalizar.py
normalizacao-0.1.3.dist-info/LICENSE
normalizacao-0.1.3.dist-info/METADATA
normalizacao-0.1.3.dist-info/WHEEL
normalizacao-0.1.3.dist-info/top_level.txt
normalizacao-0.1.3.dist-info/RECORD
